rudra_log/__init__.py
rudra_log/apis.py
rudra_log/helpers.py
rudra_log/middleware.py
rudra_log/utils.py
django_rudra_log-0.6.6.dist-info/METADATA
django_rudra_log-0.6.6.dist-info/WHEEL
django_rudra_log-0.6.6.dist-info/top_level.txt
django_rudra_log-0.6.6.dist-info/RECORD
